pga_gpt_tools/__init__.py
pga_gpt_tools/generate_image.py
pga_gpt_tools/get_okta_user.py
pga_gpt_tools/remove_background.py
pga_gpt_tools/web_scrape.py
pga_gpt_tools/web_search.py
pga_gpt_tools-0.1.1.dist-info/METADATA
pga_gpt_tools-0.1.1.dist-info/WHEEL
pga_gpt_tools-0.1.1.dist-info/top_level.txt
pga_gpt_tools-0.1.1.dist-info/RECORD
