Metadata-Version: 2.1
Name: pga-gpt-tools
Version: 0.1.1
Summary: A collection of tools for PGA AI products
Home-page: https://github.com/pgahq/pga-gpt-tools
Author: PGA Tech
Author-email: pgatech@pgahq.com
Classifier: Programming Language :: Python :: 3
Classifier: License :: OSI Approved :: MIT License
Classifier: Operating System :: OS Independent
Requires-Python: >=3.6
Requires-Dist: requests
Requires-Dist: pydantic
Requires-Dist: instructor
Requires-Dist: google-search-results
Requires-Dist: firecrawl-py
Requires-Dist: fal-client
Requires-Dist: openai
